{
  "generatedAt": "2026-07-18T15:20:00+07:00",
  "scope": "production assets under public; documentation screenshots excluded",
  "summary": {"svg": 2, "png": 3, "jpg": 0, "webp": 0, "avif": 0, "duplicates": 0, "externalImages": 0},
  "assets": [
    {"filePath":"public/favicon.svg","fileName":"favicon.svg","extension":"svg","pixelDimensions":"vector (viewBox 0 0 64 64)","aspectRatio":"1:1","fileSizeBytes":242,"usageLocations":["src/layouts/Base.astro favicon","Organization.logo"],"altText":"n/a","loadingBehavior":"browser favicon","responsiveBehavior":"vector","duplicateStatus":"unique","risk":"low","recommendation":"retain"},
    {"filePath":"public/images/trust-inspection.png","fileName":"trust-inspection.png","extension":"png","pixelDimensions":"1024x1024","aspectRatio":"1:1 source; rendered 4:3 crop","fileSizeBytes":916976,"usageLocations":["src/pages/index.astro trust gallery"],"altText":"ภาพประกอบการตรวจสอบสภาพโน้ตบุ๊คและอุปกรณ์โดยละเอียดเพื่อประเมินราคา","loadingBehavior":"lazy","responsiveBehavior":"none; fixed src, HTML 400x300","duplicateStatus":"unique","risk":"high: oversized PNG and illustration may be mistaken for evidence","recommendation":"replace with licensed real process photo; AVIF/WebP 480/768/1024, <=120 KB"},
    {"filePath":"public/images/trust-inventory.png","fileName":"trust-inventory.png","extension":"png","pixelDimensions":"1024x1024","aspectRatio":"1:1 source; rendered 4:3 crop","fileSizeBytes":806497,"usageLocations":["src/pages/index.astro trust gallery"],"altText":"ภาพประกอบตัวอย่างประเภทโน้ตบุ๊คและสินค้าไอทีเพื่อชี้แจงกลุ่มอุปกรณ์ที่รับซื้อ","loadingBehavior":"lazy","responsiveBehavior":"none; fixed src, HTML 400x300","duplicateStatus":"unique","risk":"high: oversized PNG and non-evidence illustration","recommendation":"replace with original product inventory photo; AVIF/WebP 480/768/1024, <=120 KB"},
    {"filePath":"public/images/og/default-og.png","fileName":"default-og.png","extension":"png","pixelDimensions":"1200x630","aspectRatio":"1.91:1","fileSizeBytes":46302,"usageLocations":["src/layouts/Base.astro default OG/Twitter","Organization.image"],"altText":"WINNER IT รับซื้อสินค้าไอทีในจังหวัดขอนแก่น","loadingBehavior":"social crawler only","responsiveBehavior":"fixed 1200x630","duplicateStatus":"unique; universal reuse","risk":"medium: same social image for every intent","recommendation":"retain fallback; create truthful intent-level OG variants"},
    {"filePath":"public/images/og/default-og.svg","fileName":"default-og.svg","extension":"svg","pixelDimensions":"1200x630 viewBox","aspectRatio":"1.91:1","fileSizeBytes":2545,"usageLocations":[],"altText":"n/a","loadingBehavior":"unused","responsiveBehavior":"vector","duplicateStatus":"visual source companion to PNG","risk":"low but unused production asset","recommendation":"treat as editable source or remove only after reference audit in implementation batch"}
  ]
}
